Metadata-Version: 2.1
Name: SQL-google-interface
Version: 1.4
Summary: An interface to interact between a SQL database and Google Drive folders
Home-page: https://github.com/wtkearney/SQL-google-interface
Author: William Kearney
Author-email: wtkearney@gmail.com
License: UNKNOWN
Download-URL: https://github.com/wtkearney/SQL-google-interface/archive/v1.4.tar.gz
Platform: UNKNOWN
Classifier: Programming Language :: Python :: 3
Classifier: License :: OSI Approved :: MIT License
Classifier: Operating System :: OS Independent
Requires-Python: >=3.5
